sosviz/__init__.py
sosviz/__main__.py
sosviz/bits.py
sosviz/collect/__init__.py
sosviz/collect/ip.py
sosviz/collect/irq.py
sosviz/collect/libvirt.py
sosviz/collect/ovs.py
sosviz/collect/pci.py
sosviz/collect/platform.py
sosviz/collect/software.py
sosviz/collect/topo.py
sosviz/collect/tuning.py
sosviz/output/__init__.py
sosviz/output/dot.py
sosviz/output/json.py
sosviz/output/svg.py
sosviz/output/text.py
sosviz-0.2.12.dist-info/licenses/LICENSE
sosviz-0.2.12.dist-info/METADATA
sosviz-0.2.12.dist-info/WHEEL
sosviz-0.2.12.dist-info/entry_points.txt
sosviz-0.2.12.dist-info/top_level.txt
sosviz-0.2.12.dist-info/RECORD
