Metadata-Version: 2.4
Name: sosviz
Version: 0.2.12
Summary: Information extractor from sos reports
Author-email: Robin Jarry <rjarry@redhat.com>
License: Copyright 2024 Robin Jarry
Project-URL: Repository, https://github.com/rjarry/sosviz
Requires-Python: >=3.8
License-File: LICENSE
Requires-Dist: graphviz
Dynamic: license-file
